z3c/checkversions/README.txt
z3c/checkversions/__init__.py
z3c/checkversions/base.py
z3c/checkversions/buildout.py
z3c/checkversions/buildout.txt
z3c/checkversions/installed.py
z3c/checkversions/installed.txt
z3c/checkversions/main.py
z3c/checkversions/tests.py
z3c/checkversions/testindex/zope.component/index.html
z3c/checkversions/testindex/zope.interface/index.html
z3c/checkversions/testindex2/zope.component/index.html
z3c/checkversions/testindex2/zope.interface/index.html
z3c_checkversions-3.0.dist-info/LICENSE.rst
z3c_checkversions-3.0.dist-info/METADATA
z3c_checkversions-3.0.dist-info/WHEEL
z3c_checkversions-3.0.dist-info/entry_points.txt
z3c_checkversions-3.0.dist-info/top_level.txt
z3c_checkversions-3.0.dist-info/RECORD
