Metadata-Version: 2.2
Name: z3c.checkversions
Version: 3.0
Summary: Find newer package versions on PyPI
Home-page: https://github.com/zopefoundation/z3c.checkversions
Author: Zope Foundation and Contributors
Author-email: zope-dev@zope.dev
License: ZPL-2.1
Keywords: version,buildout,packages,upgrade,zope,ztk
Classifier: Development Status :: 5 - Production/Stable
Classifier: Environment :: Console
Classifier: Intended Audience :: Developers
Classifier: License :: OSI Approved :: Zope Public License
Classifier: Programming Language :: Python :: 3.9
Classifier: Programming Language :: Python :: 3.10
Classifier: Programming Language :: Python :: 3.11
Classifier: Programming Language :: Python :: 3.12
Classifier: Programming Language :: Python :: 3.13
Classifier: Programming Language :: Python :: Implementation :: CPython
Classifier: Programming Language :: Python :: Implementation :: PyPy
Classifier: Natural Language :: English
Classifier: Operating System :: OS Independent
Classifier: Topic :: Software Development :: Quality Assurance
Classifier: Topic :: Software Development :: Libraries :: Python Modules
Classifier: Framework :: Buildout
Classifier: Framework :: Zope
Classifier: Framework :: Zope :: 3
Classifier: Framework :: Zope :: 5
Requires-Python: >=3.9
License-File: LICENSE.rst
Requires-Dist: setuptools>=8
Provides-Extra: buildout
Requires-Dist: zc.buildout; extra == "buildout"
Provides-Extra: test
Requires-Dist: zope.testing; extra == "test"
Dynamic: author
Dynamic: author-email
Dynamic: classifier
Dynamic: description
Dynamic: home-page
Dynamic: keywords
Dynamic: license
Dynamic: provides-extra
Dynamic: requires-dist
Dynamic: requires-python
Dynamic: summary
